{
  "en": {
    "legend": [
      {
        "infoType": "title",
        "content": "Data"
      },
      {
        "infoType": "text",
        "content": "Climate normals and averages are used to summarize or describe the average climatic conditions of a particular location.\n\nAt the completion of each decade, Environment and Climate Change Canada updates its climate normals for as many locations and as many climatic characteristics as possible. The climate normals, averages and extremes offered here are based on Canadian climate stations with at least 15 years of data between 1981 to 2010."
      },
      {
        "layerId": "NORMAL_station_en",
        "description": "These are Canadian climate stations during the Normals period (1981-2010) that either have records of 25 years or better during that period, or have shorter records but are needed to represent several major centres.",
        "coverIcon": "assets/images/cities.png",
        "symbologyStack": [
          {
            "image": "assets/images/blue-circle.png",
            "text": "Station"
          }
        ],
        "symbologyRenderStyle": "icons"
      },
      {
        "infoType": "title",
        "content": "Settings"
      },
      {
        "layerId": "cities",
        "coverIcon": "assets/images/cities.png",
        "symbologyStack": [],
        "name": "Cities"
      },
      {
        "layerId": "labels",
        "coverIcon": "assets/images/labels.png",
        "symbologyStack": [],
        "name": "Labels"
      }
    ],
    "supportLayers": [
      {
        "name": "Cities",
        "controls": [
          "visibility",
          "opacity",
          "settings"
        ],
        "state": {
          "opacity": 1,
          "visibility": false,
          "identify": false,
          "hovertips": false
        },
        "id": "cities",
        "url": "https://maps-cartes.dev.ec.gc.ca/arcgis/rest/services/Overlays/Cities/MapServer",
        
        "layerType": "esri-tile"
      },
      {
        "name": "Labels",
        "controls": [
          "visibility",
          "opacity",
          "settings"
        ],
        "state": {
          "opacity": 1,
          "visibility": true,
          "identify": false,
          "hovertips": false
        },
        "id": "labels",
        "url": "https://maps-cartes.services.geo.ca/server2_serveur2/rest/services/BaseMaps/CBMT_TXT_3978/MapServer",
        
        "layerType": "esri-tile"
      }
    ],
    "dataLayers": [
      {
        "name": "Climate normals",
        "nameField": "STATION_NAME",
        "controls": [
          "datatable",
          "visibility",
          "opacity",
          "symbology"
        ],
        "state": {
          "opacity": 1,
          "visibility": true,
          "identify": true,
          "hovertips": true
        },
        "fixtures": {
          "grid": {
            "columns": [
              {
                "field": "OBJECTID",
                "visible": false
              },
              {
                "field": "rvInternalCoordX",
                "visible": false
              },
              {
                "field": "rvInternalCoordY",
                "visible": false
              },
              {
                "field": "NORMAL_CODE",
                "title": "Normal code",
                "visible": true
              },
              {
                "field": "FRE_STN_OPERATOR_ACRONYM",
                "visible": false
              },
              {
                "field": "COUNTRY",
                "visible": false
              },
              {
                "field": "WMO_IDENTIFIER",
                "title": "WMO identifier",
                "visible": true
              },
              {
                "field": "CLIMATE_IDENTIFIER",
                "title": "Climate identifier",
                "visible": true
              },
              {
                "field": "HAS_MONTHLY_SUMMARY",
                "visible": false
              },
              {
                "field": "TIMEZONE",
                "title": "Time zone",
                "visible": true
              },
              {
                "field": "PROV_STATE_TERR_CODE",
                "title": "Province / Territory",
                "visible": true
              },
              {
                "field": "PUBLICATION_CODE",
                "visible": false
              },
              {
                "field": "HAS_NORMALS_DATA",
                "visible": false
              },
              {
                "field": "ENG_PROV_NAME",
                "visible": false
              },
              {
                "field": "FRE_PROV_NAME",
                "visible": false
              },
              {
                "field": "STATION_NAME",
                "title": "Station name",
                "visible": true
              },
              {
                "field": "STATION_TYPE",
                "title": "Station type",
                "visible": true
              },
              {
                "field": "ENG_STN_OPERATOR_NAME",
                "title": "Station operator",
                "visible": true
              },
              {
                "field": "ENG_STN_OPERATOR_ACRONYM",
                "visible": false
              },
              {
                "field": "LONGITUDE",
                "title": "Longitude",
                "visible": true
              },
              {
                "field": "ELEVATION",
                "title": "Elevation",
                "visible": true
              },
              {
                "field": "TC_IDENTIFIER",
                "title": "Transport Canada identifier",
                "visible": true
              },
              {
                "field": "FRE_STN_OPERATOR_NAME",
                "visible": false
              },
              {
                "field": "LATITUDE",
                "title": "Latitude",
                "visible": true
              },
              {
                "field": "DISPLAY_CODE",
                "visible": false
              }
            ]
          },
          "details": {
            "template": "normalStationTemplate"
          }
        },
        "id": "NORMAL_station_en",
        "url": "https://api.weather.gc.ca/collections/climate-stations/items?HAS_NORMALS_DATA=Y",
        "layerType": "ogc-wfs",
        "colour": "#0ca7f5",
        "xyInAttribs": false
      }
    ]
  },
  "fr": {
    "legend": [
      {
        "infoType": "title",
        "content": "Données"
      },
      {
        "infoType": "text",
        "content": "Les normales et moyennes climatiques servent à résumer ou à décrire les conditions climatiques moyennes d'un endroit donné.\n\nÀ la fin de chaque décennie, Environnement et Changement climatique Canada met à jour ses normales climatiques pour le plus grand nombre possible de stations et de caractéristiques climatiques. Les normales climatiques, moyennes et extrêmes climatiques, offertes ici reposent sur les stations climatologiques canadiennes ayant au moins 15 années de données entre 1981 à 2010."
      },
      {
        "layerId": "NORMAL_station_fr",
        "description": "Ce sont des stations climatiques canadiennes au cours de la période des Normales (1981-2010) qui ont des records de 25 ans ou plus au cours de cette période, ou qui ont des enregistrements plus courts mais sont nécessaires pour représenter plusieurs grands centres.",
        "coverIcon": "assets/images/cities.png",
        "symbologyStack": [
          {
            "image": "assets/images/blue-circle.png",
            "text": ""
          }
        ],
        "symbologyRenderStyle": "images"
      },
      {
        "infoType": "title",
        "content": "Paramètres"
      },
      {
        "layerId": "cities",
        "coverIcon": "assets/images/cities.png",
        "symbologyStack": [],
        "name": "Villes"
      },
      {
        "layerId": "labels",
        "coverIcon": "assets/images/labels.png",
        "symbologyStack": [],
        "name": "Étiquettes"
      }
    ],
    "supportLayers": [
      {
        "name": "Villes",
        "controls": [
          "visibility",
          "opacity",
          "settings"
        ],
        "state": {
          "opacity": 1,
          "visibility": false,
          "identify": false,
          "hovertips": false
        },
        "id": "cities",
        "url": "https://maps-cartes.dev.ec.gc.ca/arcgis/rest/services/Overlays/Cities/MapServer",
        
        "layerType": "esri-tile"
      },
      {
        "name": "Étiquettes",
        "controls": [
          "visibility",
          "opacity",
          "settings"
        ],
        "state": {
          "opacity": 1,
          "visibility": true,
          "identify": false,
          "hovertips": false
        },
        "id": "labels",
        "url": "https://maps-cartes.services.geo.ca/server2_serveur2/rest/services/BaseMaps/CBCT_TXT_3978/MapServer",
        
        "layerType": "esri-tile"
      }
    ],
    "dataLayers": [
      {
        "name": "Normales climatiques",
        "nameField": "STATION_NAME",
        "controls": [
          "datatable",
          "visibility",
          "opacity",
          "symbology"
        ],
        "state": {
          "opacity": 1,
          "visibility": true,
          "identify": true,
          "hovertips": true
        },
        "fixtures": {
          "grid": {
            "columns": [
              {
                "field": "OBJECTID",
                "visible": false
              },
              {
                "field": "rvInternalCoordX",
                "visible": false
              },
              {
                "field": "rvInternalCoordY",
                "visible": false
              },
              {
                "field": "NORMAL_CODE",
                "title": "Code de la normale",
                "visible": true
              },
              {
                "field": "FRE_STN_OPERATOR_ACRONYM",
                "visible": false
              },
              {
                "field": "COUNTRY",
                "visible": false
              },
              {
                "field": "WMO_IDENTIFIER",
                "title": "Identifiant de l'OMM",
                "visible": true
              },
              {
                "field": "CLIMATE_IDENTIFIER",
                "title": "Identifiant climatique",
                "visible": true
              },
              {
                "field": "HAS_MONTHLY_SUMMARY",
                "visible": false
              },
              {
                "field": "TIMEZONE",
                "title": "Fuseau horaire",
                "visible": true
              },
              {
                "field": "PROV_STATE_TERR_CODE",
                "title": "Province / Territoire",
                "visible": true
              },
              {
                "field": "PUBLICATION_CODE",
                "visible": false
              },
              {
                "field": "HAS_NORMALS_DATA",
                "visible": false
              },
              {
                "field": "ENG_PROV_NAME",
                "visible": false
              },
              {
                "field": "FRE_PROV_NAME",
                "visible": false
              },
              {
                "field": "STATION_NAME",
                "title": "Nom de la station",
                "visible": true
              },
              {
                "field": "STATION_TYPE",
                "title": "Type de station",
                "visible": true
              },
              {
                "field": "ENG_STN_OPERATOR_NAME",
                "visible": false
              },
              {
                "field": "ENG_STN_OPERATOR_ACRONYM",
                "visible": false
              },
              {
                "field": "LONGITUDE",
                "title": "Longitude",
                "visible": true
              },
              {
                "field": "ELEVATION",
                "title": "Altitude",
                "visible": true
              },
              {
                "field": "TC_IDENTIFIER",
                "title": "Identifiant de Transports Canada",
                "visible": true
              },
              {
                "field": "FRE_STN_OPERATOR_NAME",
                "title": "Opérateur de la station",
                "visible": true
              },
              {
                "field": "LATITUDE",
                "title": "Latitude",
                "visible": true
              },
              {
                "field": "DISPLAY_CODE",
                "visible": false
              }
            ]
          },
          "details": {
            "template": "normalStationTemplate"
          }
        },
        "id": "NORMAL_station_fr",
        "url": "https://api.weather.gc.ca/collections/climate-stations/items?HAS_NORMALS_DATA=Y",
        "layerType": "ogc-wfs",
        "colour": "#0ca7f5",
        "xyInAttribs": false
      }
    ]
  }
}