{
  "layers": [
      {
        "id": "wind_22",
        "layerType": "esriDynamic",
        "url": "http://maps-cartes.dev.ec.gc.ca/arcgis/rest/services/CCDS/CMIP5_WIND/MapServer",
        "state": {
          "opacity": 0.85,
          "visibility": false
        },
        "layerEntries": [{"index": 22 }],
        "controls": ["data"]
      },
      {
        "id": "wind_23",
        "layerType": "esriDynamic",
        "url": "http://maps-cartes.dev.ec.gc.ca/arcgis/rest/services/CCDS/CMIP5_WIND/MapServer",
        "state": {
          "opacity": 0.85,
          "visibility": false
        },
        "layerEntries": [{"index": 23 }],
        "controls": ["data"]
      },
      {
        "id": "wind_24",
        "layerType": "esriDynamic",
        "url": "http://maps-cartes.dev.ec.gc.ca/arcgis/rest/services/CCDS/CMIP5_WIND/MapServer",
        "state": {
          "opacity": 0.85,
          "visibility": false
        },
        "layerEntries": [{"index": 24 }],
        "controls": ["data"]
      },
      {
        "id": "wind_25",
        "layerType": "esriDynamic",
        "url": "http://maps-cartes.dev.ec.gc.ca/arcgis/rest/services/CCDS/CMIP5_WIND/MapServer",
        "state": {
          "opacity": 0.85,
          "visibility": false
        },
        "layerEntries": [{"index": 25 }],
        "controls": ["data"]
      }

  ]
}