{
  "layers": [
      {
        "id": "sico_17",
        "layerType": "esriDynamic",
        "url": "http://cipgis.canadaeast.cloudapp.azure.com/arcgis/rest/services/CMIP5/CMIP5_SICO/MapServer",
        "state": {
          "opacity": 0.85,
          "visibility": false
        },
        "layerEntries": [{"index": 17 }],
        "controls": ["data"]
      },
      {
        "id": "sico_18",
        "layerType": "esriDynamic",
        "url": "http://cipgis.canadaeast.cloudapp.azure.com/arcgis/rest/services/CMIP5/CMIP5_SICO/MapServer",
        "state": {
          "opacity": 0.85,
          "visibility": false
        },
        "layerEntries": [{"index": 18 }],
        "controls": ["data"]
      },
      {
        "id": "sico_19",
        "layerType": "esriDynamic",
        "url": "http://cipgis.canadaeast.cloudapp.azure.com/arcgis/rest/services/CMIP5/CMIP5_SICO/MapServer",
        "state": {
          "opacity": 0.85,
          "visibility": false
        },
        "layerEntries": [{"index": 19 }],
        "controls": ["data"]
      },
      {
        "id": "sico_20",
        "layerType": "esriDynamic",
        "url": "http://cipgis.canadaeast.cloudapp.azure.com/arcgis/rest/services/CMIP5/CMIP5_SICO/MapServer",
        "state": {
          "opacity": 0.85,
          "visibility": false
        },
        "layerEntries": [{"index": 20 }],
        "controls": ["data"]
      }

  ]
}